stylelens_user
