Metadata-Version: 1.0
Name: stylelens-user
Version: 0.0.5
Summary: stylelens-user
Home-page: UNKNOWN
Author: UNKNOWN
Author-email: master@bluehack.net
License: UNKNOWN
Keywords: Swagger,stylelens-user
Platform: UNKNOWN
